shrutiAI/__init__.py
shrutiAI/client.py
shrutiAI/exceptions.py
shrutiai_sdk-1.0.0.dist-info/licenses/LICENSE
shrutiai_sdk-1.0.0.dist-info/METADATA
shrutiai_sdk-1.0.0.dist-info/WHEEL
shrutiai_sdk-1.0.0.dist-info/top_level.txt
shrutiai_sdk-1.0.0.dist-info/RECORD
